[
  { "name": "Mississippi River Valley hierarchical societies", "year": 950 },
  { "name": "Leif Ericson’s Exploration", "year": 1000 },
  { "name": "Little Ice Age", "year": 1250 },
  { "name": "Tenochtitlan and the Aztec Empire", "year": 1325 },
  { "name": "Iroquois League established", "year": 1400 },
  { "name": "Portuguese explore sub-Saharan African Coast", "year": 1434 },
  { "name": "Reconquista of Spain", "year": 1492 },
  { "name": "Columbian Exchange", "year": 1492 },
  { "name": "Columbus’s first voyage to the Americas", "year": 1492 },
  { "name": "Beginning of Spanish Empire", "year": 1500 },
  { "name": "First African slaves transported to the Caribbean islands", "year": 1502 },
  { "name": "Spain Establishes the First Colony of Puerto Rico", "year": 1508 },
  { "name": "Martin Luther’s Ninety-Five Theses", "year": 1517 },
  { "name": "Hernán Cortés arrives in Mexico", "year": 1519 },
  { "name": "Hernán Cortés Conquers Aztec Empire", "year": 1521 },
  { "name": "New France", "year": 1534 },
  { "name": "New Netherlands", "year": 1624 },
  { "name": "Virginia Company Chartered", "year": 1606 },
  { "name": "Anglican Church Formed", "year": 1534 },
  { "name": "Roanoke Colony Established", "year": 1587 },
  { "name": "Jamestown Established", "year": 1607 },
  { "name": "House of Burgesses", "year": 1619 },
  { "name": "Anglo-Powhatan War", "year": 1609 },
  { "name": "Maryland Established", "year": 1632 },
  { "name": "Pilgrims Arrive in America", "year": 1620 },
  { "name": "Mayflower Compact", "year": 1620 },
  { "name": "Massachusetts Colony", "year": 1630 },
  { "name": "Santa Fe Established", "year": 1610 },
  { "name": "Pueblo Revolt", "year": 1680 },
  { "name": "Rhode Island Established", "year": 1636 },
  { "name": "Trial of Anne Hutchinson", "year": 1637 },
  { "name": "Pequot War", "year": 1636 },
  { "name": "King Philip’s War", "year": 1675 },
  { "name": "Navigation Acts", "year": 1651 },
  { "name": "Carolina Established", "year": 1663 },
  { "name": "Yamasee War", "year": 1715 },
  { "name": "Pennsylvania", "year": 1681 },
  { "name": "Slavery Comes to America", "year": 1619 },
  { "name": "First Mission in California", "year": 1769 },
  { "name": "Bacon’s Rebellion", "year": 1676 },
  { "name": "Dominion of New England", "year": 1689 },
  { "name": "Salem Witch Trials", "year": 1692 },
  { "name": "Natchez War", "year": 1729 },
  { "name": "Georgia Founded", "year": 1733 },
  { "name": "Stono Rebellion", "year": 1739 },
  { "name": "Zenger Trial", "year": 1735 },
  { "name": "Pontiac’s War", "year": 1763 },
  { "name": "Great Awakening", "year": 1730 },
  { "name": "Seven Years War/French and Indian War", "year": 1756 },
  { "name": "Albany Plan of Union", "year": 1754 },
  { "name": "Georgia Established", "year": 1733 }
]
